machinetool/__init__.py
machinetool-0.0.0.dist-info/METADATA
machinetool-0.0.0.dist-info/WHEEL
machinetool-0.0.0.dist-info/RECORD
